{"_ts":[1498907716],"_r":{"breakdown":{"html":{"bytes":[15911],"requests":[5]},"js":{"bytes":[834910],"requests":[15]},"css":{"bytes":[63704],"requests":[1]},"image":{"bytes":[1125744],"requests":[37]},"flash":{"bytes":[0],"requests":[0]},"font":{"bytes":[196819],"requests":[9]},"other":{"bytes":[5830],"requests":[10]}},"date":[1498907716],"domElements":[519],"domInteractive":[510.33333333333],"firstPaint":[359],"fullyLoaded":[7387.6666666667],"id":["170701_W3_HQK"],"loadTime":[5101],"render":[378],"SpeedIndex":[860],"TTFB":[200],"videoFrames":[[{"_i":"ms_000000.jpg","_t":0,"_vc":0},{"_i":"ms_000338.jpg","_t":338,"_vc":46},{"_i":"ms_000488.jpg","_t":488,"_vc":47},{"_i":"ms_000610.jpg","_t":610,"_vc":48},{"_i":"ms_000747.jpg","_t":747,"_vc":54},{"_i":"ms_000851.jpg","_t":851,"_vc":55},{"_i":"ms_000979.jpg","_t":979,"_vc":55},{"_i":"ms_001198.jpg","_t":1198,"_vc":99},{"_i":"ms_001343.jpg","_t":1343,"_vc":99},{"_i":"ms_001463.jpg","_t":1463,"_vc":99},{"_i":"ms_001589.jpg","_t":1589,"_vc":99},{"_i":"ms_001705.jpg","_t":1705,"_vc":99},{"_i":"ms_001805.jpg","_t":1805,"_vc":99},{"_i":"ms_001927.jpg","_t":1927,"_vc":99},{"_i":"ms_002038.jpg","_t":2038,"_vc":99},{"_i":"ms_002156.jpg","_t":2156,"_vc":99},{"_i":"ms_002270.jpg","_t":2270,"_vc":99},{"_i":"ms_002401.jpg","_t":2401,"_vc":99},{"_i":"ms_002520.jpg","_t":2520,"_vc":99},{"_i":"ms_002637.jpg","_t":2637,"_vc":99},{"_i":"ms_002749.jpg","_t":2749,"_vc":99},{"_i":"ms_002875.jpg","_t":2875,"_vc":99},{"_i":"ms_002991.jpg","_t":2991,"_vc":99},{"_i":"ms_003114.jpg","_t":3114,"_vc":99},{"_i":"ms_003214.jpg","_t":3214,"_vc":99},{"_i":"ms_003328.jpg","_t":3328,"_vc":99},{"_i":"ms_003500.jpg","_t":3500,"_vc":99},{"_i":"ms_003612.jpg","_t":3612,"_vc":99},{"_i":"ms_003739.jpg","_t":3739,"_vc":99},{"_i":"ms_003852.jpg","_t":3852,"_vc":99},{"_i":"ms_003960.jpg","_t":3960,"_vc":99},{"_i":"ms_004071.jpg","_t":4071,"_vc":99},{"_i":"ms_004189.jpg","_t":4189,"_vc":99},{"_i":"ms_004294.jpg","_t":4294,"_vc":99},{"_i":"ms_004414.jpg","_t":4414,"_vc":99},{"_i":"ms_004535.jpg","_t":4535,"_vc":99},{"_i":"ms_004659.jpg","_t":4659,"_vc":99},{"_i":"ms_004818.jpg","_t":4818,"_vc":99},{"_i":"ms_004958.jpg","_t":4958,"_vc":98},{"_i":"ms_005064.jpg","_t":5064,"_vc":98},{"_i":"ms_005207.jpg","_t":5207,"_vc":98},{"_i":"ms_005531.jpg","_t":5531,"_vc":98},{"_i":"ms_006214.jpg","_t":6214,"_vc":98},{"_i":"ms_006578.jpg","_t":6578,"_vc":99},{"_i":"ms_007023.jpg","_t":7023,"_vc":99},{"_i":"ms_007514.jpg","_t":7514,"_vc":99},{"_i":"ms_008031.jpg","_t":8031,"_vc":99},{"_i":"ms_008510.jpg","_t":8510,"_vc":99},{"_i":"ms_009011.jpg","_t":9011,"_vc":99},{"_i":"ms_009617.jpg","_t":9617,"_vc":99},{"_i":"ms_009910.jpg","_t":9910,"_vc":100}]],"visualComplete":[10257.333333333],"lighthouse":[100],"pagespeed":[88]}}